helltml/__init__.py
helltml/__main__.py
helltml/css_parser.py
helltml/html_parser.py
helltml-0.0.1.dist-info/LICENSE
helltml-0.0.1.dist-info/METADATA
helltml-0.0.1.dist-info/WHEEL
helltml-0.0.1.dist-info/top_level.txt
helltml-0.0.1.dist-info/RECORD
