Metadata-Version: 2.1
Name: helltml
Version: 0.0.1
Summary: Write you frontend using YAML
Author-email: WazWazTheDeveloper <wazwazman1@gmail.com>
Project-URL: Homepage, https://github.com/WazWazTheDeveloper/HellTML
Project-URL: Issues, https://github.com/WazWazTheDeveloper/HellTML/issues
Classifier: Programming Language :: Python :: 3
Classifier: License :: OSI Approved :: MIT License
Classifier: Operating System :: OS Independent
Requires-Python: >=3.12
License-File: LICENSE
Requires-Dist: PyYAML ==6.0.1
Requires-Dist: typer ==0.12.3
